fastdeploy/__init__.py
fastdeploy/c_lib_wrap.py
fastdeploy/code_version.py
fastdeploy/download.py
fastdeploy/fastdeploy_main.cpython-37m-x86_64-linux-gnu.so
fastdeploy/model.py
fastdeploy/runtime.py
fastdeploy/encryption/__init__.py
fastdeploy/encryption/encryption.py
fastdeploy/libs/__init__.py
fastdeploy/libs/fastdeploy_main.cpython-37m-x86_64-linux-gnu.so
fastdeploy/libs/libfastdeploy.so
fastdeploy/libs/libfastdeploy.so.1.0.7
fastdeploy/libs/third_libs/fast_tokenizer/FastTokenizer.cmake
fastdeploy/libs/third_libs/fast_tokenizer/commit.log
fastdeploy/libs/third_libs/fast_tokenizer/lib/libcore_tokenizers.so
fastdeploy/libs/third_libs/fast_tokenizer/third_party/include/Makefile.am
fastdeploy/libs/third_libs/onnxruntime/lib/libonnxruntime.so
fastdeploy/libs/third_libs/onnxruntime/lib/libonnxruntime.so.1.12.0
fastdeploy/libs/third_libs/opencv/lib64/libopencv_calib3d.so.3.4
fastdeploy/libs/third_libs/opencv/lib64/libopencv_core.so.3.4
fastdeploy/libs/third_libs/opencv/lib64/libopencv_features2d.so.3.4
fastdeploy/libs/third_libs/opencv/lib64/libopencv_flann.so.3.4
fastdeploy/libs/third_libs/opencv/lib64/libopencv_highgui.so.3.4
fastdeploy/libs/third_libs/opencv/lib64/libopencv_imgcodecs.so.3.4
fastdeploy/libs/third_libs/opencv/lib64/libopencv_imgproc.so.3.4
fastdeploy/libs/third_libs/opencv/lib64/libopencv_video.so.3.4
fastdeploy/libs/third_libs/opencv/lib64/libopencv_videoio.so.3.4
fastdeploy/libs/third_libs/openvino/runtime/3rdparty/omp/lib/libiomp5.so
fastdeploy/libs/third_libs/openvino/runtime/cmake/InferenceEngineConfig-version.cmake
fastdeploy/libs/third_libs/openvino/runtime/cmake/InferenceEngineConfig.cmake
fastdeploy/libs/third_libs/openvino/runtime/cmake/OpenVINOConfig-version.cmake
fastdeploy/libs/third_libs/openvino/runtime/cmake/OpenVINOConfig.cmake
fastdeploy/libs/third_libs/openvino/runtime/cmake/OpenVINOTargets-release.cmake
fastdeploy/libs/third_libs/openvino/runtime/cmake/OpenVINOTargets.cmake
fastdeploy_python-1.0.7.dist-info/METADATA
fastdeploy_python-1.0.7.dist-info/WHEEL
fastdeploy_python-1.0.7.dist-info/top_level.txt
fastdeploy_python-1.0.7.dist-info/RECORD
